pdb_manip_py/__init__.py
pdb_manip_py/pdb2pqr.py
pdb_manip_py/pdb_manip.py
pdb_manip_py/test/__init__.py
pdb_manip_py/test/datafiles.py
pdb_manip_py/test/test_pdb2pqr.py
pdb_manip_py/test/test_plot.py
pdb_manip_py/test/input/1D30.pdb
pdb_manip_py/test/input/1dpx.pdb
pdb_manip_py/test/input/1jd4.pdb
pdb_manip_py/test/input/1rxz.pdb
pdb_manip_py/test/input/1y0m.gro
pdb_manip_py/test/input/1y0m.pdb
pdb_manip_py/test/input/2rri.pdb
pdb_manip_py/test/input/4n1m.pdb
pdb_manip_py-1.4.2.dist-info/LICENSE
pdb_manip_py-1.4.2.dist-info/METADATA
pdb_manip_py-1.4.2.dist-info/WHEEL
pdb_manip_py-1.4.2.dist-info/top_level.txt
pdb_manip_py-1.4.2.dist-info/RECORD
