Metadata-Version: 2.1
Name: pdb-manip-py
Version: 1.4.2
Summary: Pdb_Manip_py is a python library allowing simple operations on pdb coor files.
Home-page: https://github.com/samuelmurail/pdb_manip_py
Author: Samuel Murail
Author-email: samuel.murail@univ-paris-diderot.fr
License: UNKNOWN
Platform: UNKNOWN
Classifier: Development Status :: 5 - Production/Stable
Classifier: License :: OSI Approved :: GNU General Public License v2 (GPLv2)
Classifier: Natural Language :: English
Classifier: Operating System :: OS Independent
Classifier: Programming Language :: Python :: 3
Classifier: Programming Language :: Python :: 3.8
Classifier: Programming Language :: Python :: 3.7
Classifier: Programming Language :: Python :: 3.6
Classifier: Programming Language :: Python :: 3.5
Classifier: Topic :: Scientific/Engineering :: Bio-Informatics
License-File: LICENSE
Requires-Dist: numpy
Requires-Dist: scipy (>=1.4.0)
Requires-Dist: pdb2pqr (==3.5.2)
Requires-Dist: os-command-py (==1.1.0)
